event_engine/__init__.py
event_engine/base/__init__.py
event_engine/base/c_heap_allocator.h
event_engine/base/c_strmap.c
event_engine/base/c_strmap.cpython-314-x86_64-linux-gnu.so
event_engine/base/c_strmap.h
event_engine/base/c_strmap.pxd
event_engine/base/c_strmap.pyi
event_engine/base/c_strmap.pyx
event_engine/base/xxh3.h
event_engine/base/xxhash.c
event_engine/base/xxhash.h
event_engine/capi/__init__.pxd
event_engine/capi/__init__.py
event_engine/capi/c_engine.c
event_engine/capi/c_engine.cpython-314-x86_64-linux-gnu.so
event_engine/capi/c_engine.h
event_engine/capi/c_engine.pxd
event_engine/capi/c_engine.pyi
event_engine/capi/c_engine.pyx
event_engine/capi/c_event.c
event_engine/capi/c_event.cpython-314-x86_64-linux-gnu.so
event_engine/capi/c_event.h
event_engine/capi/c_event.pxd
event_engine/capi/c_event.pyi
event_engine/capi/c_event.pyx
event_engine/capi/c_topic.c
event_engine/capi/c_topic.cpython-314-x86_64-linux-gnu.so
event_engine/capi/c_topic.h
event_engine/capi/c_topic.pxd
event_engine/capi/c_topic.pyi
event_engine/capi/c_topic.pyx
event_engine/capi/fallback_engine.py
event_engine/native/__init__.py
event_engine/native/_event.py
event_engine/native/_topic.py
event_engine/native/engine.py
event_engine/native/event.py
event_engine/native/topic.py
pyeventengine-0.4.6.post1.dist-info/METADATA
pyeventengine-0.4.6.post1.dist-info/WHEEL
pyeventengine-0.4.6.post1.dist-info/top_level.txt
pyeventengine-0.4.6.post1.dist-info/RECORD
pyeventengine-0.4.6.post1.dist-info/licenses/LICENSE
