Metadata-Version: 2.4
Name: PyEventEngine
Version: 0.4.6.post1
Summary: Python Basic EventEngine
Author-email: Han Bolun <Bolun.Han@outlook.com>
Project-URL: Homepage, https://github.com/BolunHan/PyEventEngine
Project-URL: Repository, https://github.com/BolunHan/PyEventEngine
Project-URL: Issues, https://github.com/BolunHan/PyEventEngine/issues
Classifier: Programming Language :: Python :: 3
Classifier: Programming Language :: Python :: 3.12
Classifier: Programming Language :: Python :: 3.13
Classifier: Programming Language :: Python :: 3.14
Classifier: Operating System :: OS Independent
Requires-Python: >=3.12
License-File: LICENSE
Dynamic: license-file
